{
    "title": "\u2018HOUSE OF THE DRAGON\u2019 Season 3 is the messiest thus far, suggesting that George R.R. Martin was probably right to leave the HBO show.\n\nFind out more in our review...\nhttps://discussingfilm.net/2026/06/18/house-of-the-dragon-season-3-review/",
    "url": "https://x.com/DiscussingFilm/status/2067832757842297008",
    "blocks": [
        {
            "type": "img",
            "content": "https://nitter.net/pic/card_img%2F2067832730075963392%2FRLtPA6Zm%3Fformat%3Djpg%26name%3D800x419"
        }
    ]
}